jahn_teller_dynamics/Exe.py
jahn_teller_dynamics/__init__.py
jahn_teller_dynamics/io/JT_config_file_parsing.py
jahn_teller_dynamics/io/VASP.py
jahn_teller_dynamics/io/__init__.py
jahn_teller_dynamics/io/plotting.py
jahn_teller_dynamics/io/user_workflow.py
jahn_teller_dynamics/io/xml_parser.py
jahn_teller_dynamics/io/config/__init__.py
jahn_teller_dynamics/io/config/atom_parser.py
jahn_teller_dynamics/io/config/constants.py
jahn_teller_dynamics/io/config/field_parser.py
jahn_teller_dynamics/io/config/parameter_extractor.py
jahn_teller_dynamics/io/config/parser.py
jahn_teller_dynamics/io/config/reader.py
jahn_teller_dynamics/io/config/section_detector.py
jahn_teller_dynamics/io/config/writer.py
jahn_teller_dynamics/io/file_io/__init__.py
jahn_teller_dynamics/io/file_io/csv_writer.py
jahn_teller_dynamics/io/file_io/results_formatter.py
jahn_teller_dynamics/io/file_io/vasp.py
jahn_teller_dynamics/io/file_io/xml_parser.py
jahn_teller_dynamics/io/theory/__init__.py
jahn_teller_dynamics/io/theory/builder.py
jahn_teller_dynamics/io/theory/calculator.py
jahn_teller_dynamics/io/utils/__init__.py
jahn_teller_dynamics/io/utils/file_utils.py
jahn_teller_dynamics/io/utils/path_manager.py
jahn_teller_dynamics/io/visualization/__init__.py
jahn_teller_dynamics/io/visualization/plotter.py
jahn_teller_dynamics/io/workflow/__init__.py
jahn_teller_dynamics/io/workflow/orchestrator.py
jahn_teller_dynamics/math/__init__.py
jahn_teller_dynamics/math/braket_formalism.py
jahn_teller_dynamics/math/eigen_solver.py
jahn_teller_dynamics/math/maths.py
jahn_teller_dynamics/math/matrix_mechanics.py
jahn_teller_dynamics/physics/__init__.py
jahn_teller_dynamics/physics/constants.py
jahn_teller_dynamics/physics/jahn_teller_theory.py
jahn_teller_dynamics/physics/quantum_physics.py
jahn_teller_dynamics/physics/quantum_system.py
jahn_teller_dynamics/physics/hamiltonians/__init__.py
jahn_teller_dynamics/physics/hamiltonians/djt_hamiltonian.py
jahn_teller_dynamics-1.0.2.dist-info/LICENSE
jahn_teller_dynamics-1.0.2.dist-info/METADATA
jahn_teller_dynamics-1.0.2.dist-info/WHEEL
jahn_teller_dynamics-1.0.2.dist-info/entry_points.txt
jahn_teller_dynamics-1.0.2.dist-info/top_level.txt
jahn_teller_dynamics-1.0.2.dist-info/RECORD
