Metadata-Version: 2.1
Name: jahn-teller-dynamics
Version: 1.0.2
Summary: Dynamic Jahn-Teller Effect Calculator
Home-page: https://github.com/tbalu98/Jahn-Teller-Dynamics
Author: Balázs Tóth
Author-email: toth.balazs@wigner.hun-ren.hu
License: GPLv3
Platform: UNKNOWN
Classifier: Development Status :: 5 - Production/Stable
Classifier: Intended Audience :: Science/Research
Classifier: Topic :: Scientific/Engineering :: Physics
Classifier: License :: OSI Approved :: GNU General Public License v3 (GPLv3)
Classifier: Programming Language :: Python :: 3
Classifier: Programming Language :: Python :: 3.10
Classifier: Programming Language :: Python :: 3.11
Classifier: Programming Language :: Python :: 3.12
Requires-Python: >=3.10
License-File: LICENSE
Requires-Dist: contourpy>=1.3.0
Requires-Dist: cycler>=0.12.0
Requires-Dist: fonttools>=4.54.0
Requires-Dist: kiwisolver>=1.4.0
Requires-Dist: matplotlib>=3.9.0
Requires-Dist: numpy>=2.1.0
Requires-Dist: packaging>=24.0
Requires-Dist: pandas>=2.2.0
Requires-Dist: pillow>=10.4.0
Requires-Dist: pyparsing>=3.1.0
Requires-Dist: python-dateutil>=2.9.0
Requires-Dist: pytz>=2024.0
Requires-Dist: scipy>=1.14.0
Requires-Dist: six>=1.16.0
Requires-Dist: tzdata>=2024.0
